flash_perceiver/__init__.py
flash_perceiver/adapters.py
flash_perceiver/perceiver.py
flash_perceiver/utils/__init__.py
flash_perceiver/utils/encodings.py
flash_perceiver/utils/training.py
flash_perceiver-0.2.0.dist-info/METADATA
flash_perceiver-0.2.0.dist-info/WHEEL
flash_perceiver-0.2.0.dist-info/RECORD
