Metadata-Version: 2.1
Name: flash-perceiver
Version: 0.2.0
Summary: Fast and memory efficient PyTorch implementation of the Perceiver with FlashAttention.
Author: Kristian Klemon
Author-email: kristian.klemon@gmail.com
Requires-Python: >=3.9
Classifier: Programming Language :: Python :: 3
Classifier: Programming Language :: Python :: 3.9
Classifier: Programming Language :: Python :: 3.10
Classifier: Programming Language :: Python :: 3.11
Requires-Dist: einops (>=0.7.0,<0.8.0)
